[{"name":"ACLEDA BANK (LAO) LTD","city":"VIENTIANE","branch":"","swift":"ACLBLALA"},{"name":"AGRICULTURAL PROMOTION BANK","city":"VIENTIANE","branch":"","swift":"AGPBLALA"},{"name":"ANZ BANK (LAO) LIMITED","city":"VIENTIANE","branch":"","swift":"VCBBLALA"},{"name":"BANGKOK BANK PLC VIENTIANE BRANCH","city":"VIENTIANE","branch":"","swift":"BKKBLALA"},{"name":"BANK OF THE LAO P.D.R.","city":"VIENTIANE","branch":"","swift":"LPDRLALA"},{"name":"BANQUE FRANCO LAO LTD","city":"VIENTIANE","branch":"","swift":"BFLLLALA"},{"name":"BANQUE POUR LE COMMERCE EXTERIEUR LAO PUBLIC","city":"KHAMMOUANE","branch":"(KHAMMOUANE BRANCH)","swift":"COEBLALAKMN"},{"name":"BANQUE POUR LE COMMERCE EXTERIEUR LAO PUBLIC","city":"LUANGNAMTHA","branch":"(LUANGNAMTHA BRANCH)","swift":"COEBLALALNT"},{"name":"BANQUE POUR LE COMMERCE EXTERIEUR LAO PUBLIC","city":"LUANGPRABANG","branch":"(LUANGPRABANG BRANCH)","swift":"COEBLALALBP"},{"name":"BANQUE POUR LE COMMERCE EXTERIEUR LAO PUBLIC","city":"OUDOMXAY","branch":"(OUDOMXAY BRANCH)","swift":"COEBLALAODX"},{"name":"BANQUE POUR LE COMMERCE EXTERIEUR LAO PUBLIC","city":"PAKSE","branch":"(CHAMPASACK BRANCH)","swift":"COEBLALACPS"},{"name":"BANQUE POUR LE COMMERCE EXTERIEUR LAO PUBLIC","city":"SAVANNAKHET","branch":"(SAVANNAKHET BRANCH)","swift":"COEBLALASVN"},{"name":"BANQUE POUR LE COMMERCE EXTERIEUR LAO PUBLIC","city":"VIENTIANE","branch":"","swift":"COEBLALA"},{"name":"INDOCHINA BANK LTD","city":"VIENTIANE","branch":"","swift":"IDCBLALA"},{"name":"INDUSTRIAL AND COMMERCIAL BANK OF CHINA LIMITED VIENTIANE BRANCH","city":"VIENTIANE","branch":"","swift":"ICBKLALA"},{"name":"INTERNATIONAL COMMERCIAL BANK (LAO) LTD","city":"VIENTIANE","branch":"","swift":"LICBLALA"},{"name":"JOINT DEVELOPMENT BANK","city":"VIENTIANE","branch":"","swift":"JDBKLALA"},{"name":"LAO CONSTRUCTION BANK","city":"VIENTIANE","branch":"","swift":"LCBVLALA"},{"name":"LAO DEVELOPMENT BANK","city":"VIENTIANE","branch":"","swift":"LDBBLALA"},{"name":"LAO VIET BANK","city":"CHAMPASAK","branch":"(CHAMPASAK BRANCH)","swift":"LAOVLALACPS"},{"name":"LAO VIET BANK","city":"VIENTIANE","branch":"","swift":"LAOVLALA"},{"name":"MAYBANK LAO","city":"VIENTIANE","branch":"","swift":"MBBELALA"},{"name":"PHONGSAVANH BANK LTD","city":"VIENTIANE","branch":"","swift":"PSVBLALA"},{"name":"PUBLIC BANK VIENTIANE BRANCH LAO P.D.R.","city":"VIENTIANE","branch":"","swift":"PBBELALA"},{"name":"SAIGON HANOI COMMERCIAL JOINT STOCK BANK LAOS BRANCH","city":"CHAMPASAK","branch":"","swift":"SHBALALA"},{"name":"SIAM COMMERCIAL BANK PCL. THE","city":"VIENTIANE","branch":"","swift":"SICOLALA"},{"name":"ST BANK CO. LTD","city":"VIENTIANE","branch":"","swift":"STBDLALA"},{"name":"VIETNAM JOINT STOCK COMMERCIAL BANK FOR INDUSTRY AND TRADE LAO P.D.P BRANCH","city":"VIENTIANE","branch":"","swift":"ICBVLALA"}]